datahub.cp312-win_amd64.pyd
datahub.pyi
datahub/__init__.pyi
datahub/datacache.pyi
datahub/datahub.pyi
datahub/setting.pyi
datahub/ats/client_sdk.pyi
datahub/dbo/database.pyi
datahub/dbo/pg.pyi
datahub/dbo/redis_stream.pyi
datahub/dbo/sr.pyi
datahub/protos/client_msg.pyi
datahub/protos/client_pb2.pyi
datahub/protos/common_pb2.pyi
datahub/protos/management_pb2.pyi
datahub/protos/position_pb2.pyi
datahub/protos/query_pb2.pyi
datahub/protos/quote_pb2.pyi
datahub/protos/signal_pb2.pyi
datahub/protos/strategy_pb2.pyi
datahub/protos/trade_pb2.pyi
datahub/utils/__init__.pyi
datahub/utils/logger.pyi
datahub/utils/sftp.pyi
datahub/utils/monitor/__init__.pyi
datahub/utils/monitor/base.pyi
datahub/utils/monitor/feishu.pyi
datahub_binary-1.9.9.dist-info/METADATA
datahub_binary-1.9.9.dist-info/WHEEL
datahub_binary-1.9.9.dist-info/top_level.txt
datahub_binary-1.9.9.dist-info/RECORD
