Metadata-Version: 2.4
Name: datahub_binary
Version: 1.9.9
Summary: A comprehensive Python library for data processing, integration, and management.
Requires-Python: <3.13,>=3.10
Requires-Dist: SQLAlchemy>=2.0.0
Requires-Dist: httpx[socks]>=0.28.0
Requires-Dist: starrocks>=1.0.0
Requires-Dist: polars-lts-cpu==1.26.0; sys_platform == "darwin"
Requires-Dist: polars==1.26.0; sys_platform != "darwin"
Requires-Dist: loguru>=0.7.3
Requires-Dist: numpy>=1.0.0
Requires-Dist: protobuf>=6.30.1
Requires-Dist: redis>=5.2.1
Requires-Dist: psycopg2-binary>=2.9.10
Requires-Dist: paramiko>=3.5.1
Requires-Dist: toml>=0.10.0
Requires-Dist: pydantic>=2.11.3
Requires-Dist: lark-oapi>=1.4.22
Requires-Dist: pyzmq>=26.4.0
Requires-Dist: sortedcontainers>=2.4.0
Requires-Dist: mypy>=1.18.1
Requires-Dist: tzdata>=2025.2
